setup.py
pyhfo/__init__.py
pyhfo/functions.py
pyhfo.egg-info/PKG-INFO
pyhfo.egg-info/SOURCES.txt
pyhfo.egg-info/dependency_links.txt
pyhfo.egg-info/not-zip-safe
pyhfo.egg-info/requires.txt
pyhfo.egg-info/top_level.txt