Metadata-Version: 1.0
Name: pyhfo
Version: 1.0.0-Beta
Summary: Python Package to analyse High Frequency Oscillations in ECoG data
Home-page: https://github.com/andersonbrisil/pyhfo.git
Author: Anderson Brito da Silva
Author-email: a.brito-da-silva1@newcastle.ac.uk
License: MIT
Platform: UNKNOWN
